[1,0,0,[["cc.JsonAsset",["_name","json"],1]],[[0,0,1,3]],[[0,"ResourcesProdution",{"OilFactory_lvl_1":[{"product":"steel","time":20,"count":5},{"product":"oil","time":15,"count":7},{"product":"stuff","time":12,"count":9}],"OilFactory_lvl_2":[{"product":"steel","time":20,"count":15},{"product":"oil","time":17,"count":51},{"product":"stuff","time":12,"count":11}],"OilFactory_lvl_3":[{"product":"steel","time":5,"count":50},{"product":"oil","time":5,"count":50},{"product":"stuff","time":25,"count":50}]}]],0,0,[],[],[]]
